Day02_RTL_Simulation/rtl/alu32_pipeline.v
module alu32_pipeline (
    input  wire        clk,
    input  wire        rst,
    input  wire [31:0] A,
    input  wire [31:0] B,
    input  wire [2:0]  op,
    output reg  [31:0] Y
);
reg [31:0] alu_result;
reg [31:0] A_reg;
reg [31:0] B_reg;
reg [2:0]  op_reg;

always @(*) begin
    case (op_reg)
        3'b000: alu_result = A_reg + B_reg;
	3'b001: alu_result = A_reg - B_reg;
	3'b010: alu_result = A_reg & B_reg;
	3'b011: alu_result = A_reg | B_reg;
	3'b100: alu_result = A_reg ^ B_reg;
	default: alu_result = 32'b0;
    endcase
end

always @(posedge clk) begin
    if (rst) begin
        A_reg <= 32'b0;
        B_reg <= 32'b0;
        op_reg <= 3'b000;
        Y <= 32'b0;
    end
    else begin
        A_reg <= A;
        B_reg <= B;
        op_reg <= op;
        Y <= alu_result;
    end
end

endmodule

Day02_RTL_Simulation/tb/tb_alu32_pipeline.v
`timescale 1ns/1ps

module tb_alu32_pipeline;

reg clk;
reg rst;
reg [31:0] A;
reg [31:0] B;
reg [2:0]  op;

wire [31:0] Y;

alu32_pipeline dut (
    .clk(clk),
    .rst(rst),
    .A(A),
    .B(B),
    .op(op),
    .Y(Y)
);

initial begin
    clk = 1'b0;
    forever #5 clk = ~clk;
end

initial begin
    rst = 1'b1;
    A   = 32'b0;
    B   = 32'b0;
    op  = 3'b000;

    #12;
    rst = 1'b0;
end

initial begin
    $dumpfile("../waveforms/alu32_pipeline.vcd");
    $dumpvars(0, tb_alu32_pipeline);

    #15;
    A  = 32'd10;
    B  = 32'd20;
    op = 3'b000;   // ADD
    #11;
    $display("ADD: A=%0d B=%0d Y=%0d", A, B, Y);

    @(negedge clk);
    A  = 32'd30;
    B  = 32'd10;
    op = 3'b001;   // SUB
    
    @(posedge clk);
    @(posedge clk);
    #1;
    $display("SUB: A=%0d B=%0d Y=%0d", A, B, Y);

    @(negedge clk);
    A  = 32'h0F0F0F0F;
    B  = 32'h00FF00FF;
    op = 3'b010;   // AND
    
    @(posedge clk);
    @(posedge clk);
    #1;  
    $display("AND: A=%h B=%h Y=%h", A, B, Y);

    @(negedge clk);
    A  = 32'h0F0F0F0F;
    B  = 32'h00FF00FF;
    op = 3'b011;   // OR
    
    @(posedge clk);
    @(posedge clk);
    #1;
    $display("OR : A=%h B=%h Y=%h", A, B, Y);

    @(negedge clk);
    A  = 32'h0F0F0F0F;
    B  = 32'h00FF00FF;
    op = 3'b100;   // XOR
    
    @(posedge clk);
    @(posedge clk);
    #1;
    $display("XOR: A=%h B=%h Y=%h", A, B, Y);

    $finish;

end

endmodule

Day02_RTL_Simulation/waveforms/alu32_pipeline.vcd
$date
	Fri Sep 18 11:24:55 2026
$end
$version
	Icarus Verilog
$end
$timescale
	1ps
$end
$scope module tb_alu32_pipeline $end
$var wire 32 ! Y [31:0] $end
$var reg 32 " A [31:0] $end
$var reg 32 # B [31:0] $end
$var reg 1 $ clk $end
$var reg 3 % op [2:0] $end
$var reg 1 & rst $end
$scope module dut $end
$var wire 32 ' A [31:0] $end
$var wire 32 ( B [31:0] $end
$var wire 1 $ clk $end
$var wire 3 ) op [2:0] $end
$var wire 1 & rst $end
$var reg 32 * A_reg [31:0] $end
$var reg 32 + B_reg [31:0] $end
$var reg 32 , Y [31:0] $end
$var reg 32 - alu_result [31:0] $end
$var reg 3 . op_reg [2:0] $end
$upscope $end
$upscope $end
$enddefinitions $end
#0
$dumpvars
bx .
bx -
bx ,
bx +
bx *
b0 )
b0 (
b0 '
1&
b0 %
0$
b0 #
b0 "
bx !
$end
#5000
b0 -
b0 !
b0 ,
b0 .
b0 +
b0 *
1$
#10000
0$
#12000
0&
#15000
b11110 -
b10100 +
b1010 *
1$
b10100 #
b10100 (
b1010 "
b1010 '
#20000
0$
#25000
b11110 !
b11110 ,
1$
#30000
b1 %
b1 )
b1010 #
b1010 (
b11110 "
b11110 '
0$
#35000
b10100 -
b1 .
b1010 +
b11110 *
1$
#40000
0$
#45000
b10100 !
b10100 ,
1$
#50000
b10 %
b10 )
b111111110000000011111111 #
b111111110000000011111111 (
b1111000011110000111100001111 "
b1111000011110000111100001111 '
0$
#55000
b11110000000000001111 -
b10 .
b111111110000000011111111 +
b1111000011110000111100001111 *
1$
#60000
0$
#65000
b11110000000000001111 !
b11110000000000001111 ,
1$
#70000
b11 %
b11 )
0$
#75000
b1111111111110000111111111111 -
b11 .
1$
#80000
0$
#85000
b1111111111110000111111111111 !
b1111111111110000111111111111 ,
1$
#90000
b100 %
b100 )
0$
#95000
b1111111100000000111111110000 -
b100 .
1$
#100000
0$
#105000
b1111111100000000111111110000 !
b1111111100000000111111110000 ,
1$
